cvutil3d/__init__.py
cvutil3d/render.py
cvutil3d-0.0.1.dist-info/LICENSE
cvutil3d-0.0.1.dist-info/METADATA
cvutil3d-0.0.1.dist-info/WHEEL
cvutil3d-0.0.1.dist-info/top_level.txt
cvutil3d-0.0.1.dist-info/RECORD
